ansys/turbogrid/api/__init__.pyc
ansys/turbogrid/api/cueengine_core.pyc
ansys/turbogrid/api/cueengine_read_messenger.pyc
ansys/turbogrid/api/cueengine_send_messenger.pyc
ansys/turbogrid/api/help_utils.pyc
ansys/turbogrid/api/pyturbogrid_core.pyc
ansys/turbogrid/api/pyturbogrid_core.pyi
ansys/turbogrid/api/server_log_level.pyc
ansys/turbogrid/api/CCL/__init__.pyc
ansys/turbogrid/api/CCL/ccl_change_observer_interface.pyc
ansys/turbogrid/api/CCL/ccl_constants.pyc
ansys/turbogrid/api/CCL/ccl_object.pyc
ansys/turbogrid/api/CCL/ccl_object_db.pyc
ansys/turbogrid/api/CCL/ccl_object_factory.pyc
ansys/turbogrid/api/CCL/ccl_rules_parser.pyc
ansys/turbogrid/api/CCL/ccl_utils.pyc
ansys/turbogrid/api/CCL/object_db_service_interface.pyc
ansys/turbogrid/api/CCL/remote_engine_interface.pyc
ansys/turbogrid/api/CCL/state_ccl_object.pyc
ansys_turbogrid_api-0.5.4.dist-info/METADATA
ansys_turbogrid_api-0.5.4.dist-info/WHEEL
ansys_turbogrid_api-0.5.4.dist-info/top_level.txt
ansys_turbogrid_api-0.5.4.dist-info/RECORD
