Metadata-Version: 2.1
Name: ansys-turbogrid-api
Version: 0.5.4
Home-page: https://github.com/ansys-internal/ansys-api-turbogrid
Author: ANSYS, Inc.
Author-email: pyansys.core@ansys.com
Maintainer: ANSYS, Inc.
Maintainer-email: pyansys.core@ansys.com
License: MIT
Project-URL: Documentation, https://github.com/ansys-internal/ansys-api-turbogrid/#readme
Project-URL: Source, https://github.com/ansys-internal/ansys-api-turbogrid/
Project-URL: Tracker, https://github.com/ansys-internal/ansys-api-turbogrid/issues/
Requires-Python: >=3.8
License-File: LICENSE
Requires-Dist: ansys-platform-instancemanagement ~=1.0
Requires-Dist: toml >=0.10.0
Requires-Dist: pyvista >=0.45.0
